microsoft_agents_a365/tooling/extensions/semantickernel/__init__.py
microsoft_agents_a365/tooling/extensions/semantickernel/services/__init__.py
microsoft_agents_a365/tooling/extensions/semantickernel/services/mcp_tool_registration_service.py
microsoft_agents_a365_tooling_extensions_semantickernel-0.2.1.dev9.dist-info/METADATA
microsoft_agents_a365_tooling_extensions_semantickernel-0.2.1.dev9.dist-info/WHEEL
microsoft_agents_a365_tooling_extensions_semantickernel-0.2.1.dev9.dist-info/top_level.txt
microsoft_agents_a365_tooling_extensions_semantickernel-0.2.1.dev9.dist-info/RECORD
